README.md
setup.py
workout.py
workout.py.egg-info/PKG-INFO
workout.py.egg-info/SOURCES.txt
workout.py.egg-info/dependency_links.txt
workout.py.egg-info/entry_points.txt
workout.py.egg-info/not-zip-safe
workout.py.egg-info/requires.txt
workout.py.egg-info/top_level.txt