Metadata-Version: 2.1
Name: workout.py
Version: 1.0.0
Summary: Workout buddy
Home-page: https://www.devdungeon.com
Author: DevDungeon
Author-email: nanodano@devdungeon.com
License: GPL-3.0
Platform: UNKNOWN
